oci/VERSION
oci/__init__.py
oci/__main__.py
oci/auth.py
oci/aws.py
oci/client.py
oci/client_async.py
oci/convert.py
oci/docker.py
oci/merge.py
oci/model.py
oci/platform.py
oci/util.py
oci/workarounds.py
gardener_oci-1.2740.0.dist-info/LICENSE
gardener_oci-1.2740.0.dist-info/METADATA
gardener_oci-1.2740.0.dist-info/WHEEL
gardener_oci-1.2740.0.dist-info/entry_points.txt
gardener_oci-1.2740.0.dist-info/top_level.txt
gardener_oci-1.2740.0.dist-info/RECORD
