Metadata-Version: 2.1
Name: gardener-oci
Version: 1.2740.0
Summary: Gardener OCI lib
Requires-Python: >=3.10
License-File: LICENSE
Requires-Dist: dacite
Requires-Dist: python-dateutil
Requires-Dist: requests
Requires-Dist: www-authenticate
Provides-Extra: async
Requires-Dist: aiohttp ; extra == 'async'
